forge/__init__.py
forge/__main__.py
forge/actions/__init__.py
forge/actions/file_system/files.py
forge/actions/finish.py
forge/actions/registry.py
forge/actions/web/web_search.py
forge/actions/web/web_selenium.py
forge/agent.py
forge/app.py
forge/db.py
forge/llm.py
forge/memory/__init__.py
forge/memory/chroma_memstore.py
forge/memory/memstore.py
forge/memory/memstore_test.py
forge/prompts/gpt-3.5-turbo/role_selection.j2
forge/prompts/gpt-3.5-turbo/system-format.j2
forge/prompts/gpt-3.5-turbo/task-step.j2
forge/prompts/techniques/chain-of-thought.j2
forge/prompts/techniques/expert.j2
forge/prompts/techniques/few-shot.j2
forge/sdk/__init__.py
forge/sdk/agent.py
forge/sdk/agent_test.py
forge/sdk/db.py
forge/sdk/db_test.py
forge/sdk/errors.py
forge/sdk/forge_log.py
forge/sdk/middlewares.py
forge/sdk/model.py
forge/sdk/prompting.py
forge/sdk/routes/__init__.py
forge/sdk/routes/agent_protocol.py
forge/sdk/workspace.py
forge/sdk/workspace_test.py
autogpt_forge-0.1.4.dist-info/METADATA
autogpt_forge-0.1.4.dist-info/WHEEL
autogpt_forge-0.1.4.dist-info/RECORD
