Metadata-Version: 2.1
Name: AutoGPT-Forge
Version: 0.1.4
Summary: 
License: MIT
Author: Craig Swift
Author-email: craigswift13@gmail.com
Requires-Python: >=3.10,<4.0
Classifier: License :: OSI Approved :: MIT License
Classifier: Programming Language :: Python :: 3
Classifier: Programming Language :: Python :: 3.10
Classifier: Programming Language :: Python :: 3.11
Provides-Extra: benchmark
Requires-Dist: aiohttp (>=3.8.5,<4.0.0)
Requires-Dist: bs4 (>=0.0.1,<0.0.2)
Requires-Dist: chromadb (>=0.4.10,<0.5.0)
Requires-Dist: colorlog (>=6.7.0,<7.0.0)
Requires-Dist: duckduckgo-search (>=4.0.0,<5.0.0)
Requires-Dist: google-cloud-storage (>=2.13.0,<3.0.0)
Requires-Dist: jinja2 (>=3.1.2,<4.0.0)
Requires-Dist: litellm (>=1.17.9,<2.0.0)
Requires-Dist: openai (>=1.7.2,<2.0.0)
Requires-Dist: python-dotenv (>=1.0.0,<2.0.0)
Requires-Dist: python-multipart (>=0.0.7,<0.0.8)
Requires-Dist: selenium (>=4.13.0,<5.0.0)
Requires-Dist: sqlalchemy (>=2.0.19,<3.0.0)
Requires-Dist: tenacity (>=8.2.2,<9.0.0)
Requires-Dist: toml (>=0.10.2,<0.11.0)
Requires-Dist: uvicorn (>=0.23.2,<0.24.0)
Requires-Dist: webdriver-manager (>=4.0.1,<5.0.0)
